{ "_id" : { "$oid" : "5ae12f0b0710803ffca5fbd0" }, "bloodDonorName" : "Adane Mulugeta", "bloodDonorEmail" : "adu24gmail.com", "bloodDonorAddress" : "Ledeta , Addis Ababa , Ethiopia", "bloodDonorPhone" : "+251924784517", "selectedSex" : "Male", "bloodDonorAge" : 25, "selectedBloodGroup" : "A+" }
{ "_id" : { "$oid" : "5ae13328fa890600d0f849c0" }, "bloodDonorName" : "Neguse Abebe", "bloodDonorEmail" : "abebe21neguse@hotmail.com", "bloodDonorAddress" : "Bole , Addis Ababa , Ethiopia", "bloodDonorPhone" : "+251924784517", "selectedSex" : "Male", "bloodDonorAge" : 26, "selectedBloodGroup" : "B+" }
{ "_id" : { "$oid" : "5ae37d1763d25e0494470db5" }, "bloodDonorName" : "ff", "bloodDonorEmail" : "gfdg", "bloodDonorAddress" : "bole", "bloodDonorPhone" : "0911787878", "selectedSex" : "Male", "bloodDonorAge" : 0, "selectedBloodGroup" : "A+" }
{ "_id" : { "$oid" : "5b08a9e6ee20d0900c2f01a3" }, "bloodDonorName" : "Abi", "bloodDonorEmail" : "abi@gmail.com", "bloodDonorAddress" : "Ethiopia", "bloodDonorPhone" : "0978458963", "selectedSex" : "Female", "bloodDonorAge" : 45, "selectedBloodGroup" : "A+" }
{ "_id" : { "$oid" : "5b08ad3ee0065d9e4075b777" }, "bloodDonorName" : "Alex", "bloodDonorEmail" : "Abrham", "bloodDonorAddress" : "Ethiopia", "bloodDonorPhone" : "0958741263", "selectedSex" : "Male", "bloodDonorAge" : null, "selectedBloodGroup" : "A+" }
{ "_id" : { "$oid" : "5b08ad63e0065d9e4075b779" }, "bloodDonorName" : "Alex", "bloodDonorEmail" : "Abrham", "bloodDonorAddress" : "NewYork", "bloodDonorPhone" : "0958741263", "selectedSex" : "Male", "bloodDonorAge" : -9, "selectedBloodGroup" : "A+" }
{ "_id" : { "$oid" : "5b08af0d224d839b4436c664" }, "bloodDonorName" : "Donor Me", "bloodDonorEmail" : "me@me.com", "bloodDonorAddress" : "pa", "bloodDonorPhone" : "0974852136", "selectedSex" : "Male", "bloodDonorAge" : 48, "selectedBloodGroup" : "A+" }
{ "_id" : { "$oid" : "5b0bfd9e33d6e33428bf714e" }, "bloodDonorName" : "John Doe", "bloodDonorEmail" : "Doe@gmail.com", "bloodDonorAddress" : "Estonia", "bloodDonorPhone" : "0912457896", "selectedSex" : "Male", "bloodDonorAge" : 45, "selectedBloodGroup" : "A-" }
{ "_id" : { "$oid" : "5b0bfdda33d6e33428bf7150" }, "bloodDonorName" : "Kirubel ", "bloodDonorEmail" : "kira@gmail.com", "bloodDonorAddress" : "kiru@gmail.com", "bloodDonorPhone" : "09124545522", "selectedSex" : "Male", "bloodDonorAge" : 26, "selectedBloodGroup" : "A+" }
{ "_id" : { "$oid" : "5b0bfe47d329fb1914a0fc46" }, "bloodDonorName" : "Mikias", "bloodDonorEmail" : "mikiyoyo545@yahoo.com", "bloodDonorAddress" : "Addis City ", "bloodDonorPhone" : "0958748521", "selectedSex" : "Male", "bloodDonorAge" : 27, "selectedBloodGroup" : "A+" }
{ "_id" : { "$oid" : "5b2cba824983f130ec8410a3" }, "bloodDonorName" : "Adonias", "bloodDonorEmail" : "hell@gmai.com", "bloodDonorAddress" : "Addis City", "bloodDonorPhone" : "0911223344", "selectedSex" : "Male", "bloodDonorAge" : 34, "selectedBloodGroup" : "A-" }
